easymix/__init__.py
easymix-0.8.dist-info/LICENSE
easymix-0.8.dist-info/METADATA
easymix-0.8.dist-info/WHEEL
easymix-0.8.dist-info/top_level.txt
easymix-0.8.dist-info/RECORD
